jupyterlab_cognos_dashboard_embedded/__init__.py
jupyterlab_cognos_dashboard_embedded/labextension/package.json
jupyterlab_cognos_dashboard_embedded/labextension/static/0cc0f627985d8b26b1854b06cadef9aa.png
jupyterlab_cognos_dashboard_embedded/labextension/static/534.04ddf3f09961d9135c6c.js
jupyterlab_cognos_dashboard_embedded/labextension/static/568.ace8cf714cca1412cee0.js
jupyterlab_cognos_dashboard_embedded/labextension/static/755.99b08a2d6ec3484bb243.js
jupyterlab_cognos_dashboard_embedded/labextension/static/755.99b08a2d6ec3484bb243.js.LICENSE.txt
jupyterlab_cognos_dashboard_embedded/labextension/static/d1afcda6edbc28aa01a7f793d80acad7.png
jupyterlab_cognos_dashboard_embedded/labextension/static/remoteEntry.af1d0af7af5221d279fa.js
jupyterlab_cognos_dashboard_embedded/labextension/static/style.js
jupyterlab_cognos_dashboard_embedded-3.0.0.data/data/share/jupyter/labextensions/jupyterlab-cognos-dashboard-embedded/install.json
jupyterlab_cognos_dashboard_embedded-3.0.0.data/data/share/jupyter/labextensions/jupyterlab-cognos-dashboard-embedded/package.json
jupyterlab_cognos_dashboard_embedded-3.0.0.data/data/share/jupyter/labextensions/jupyterlab-cognos-dashboard-embedded/static/0cc0f627985d8b26b1854b06cadef9aa.png
jupyterlab_cognos_dashboard_embedded-3.0.0.data/data/share/jupyter/labextensions/jupyterlab-cognos-dashboard-embedded/static/534.04ddf3f09961d9135c6c.js
jupyterlab_cognos_dashboard_embedded-3.0.0.data/data/share/jupyter/labextensions/jupyterlab-cognos-dashboard-embedded/static/568.ace8cf714cca1412cee0.js
jupyterlab_cognos_dashboard_embedded-3.0.0.data/data/share/jupyter/labextensions/jupyterlab-cognos-dashboard-embedded/static/755.99b08a2d6ec3484bb243.js
jupyterlab_cognos_dashboard_embedded-3.0.0.data/data/share/jupyter/labextensions/jupyterlab-cognos-dashboard-embedded/static/755.99b08a2d6ec3484bb243.js.LICENSE.txt
jupyterlab_cognos_dashboard_embedded-3.0.0.dist-info/LICENSE
jupyterlab_cognos_dashboard_embedded-3.0.0.dist-info/METADATA
jupyterlab_cognos_dashboard_embedded-3.0.0.dist-info/WHEEL
jupyterlab_cognos_dashboard_embedded-3.0.0.dist-info/top_level.txt
jupyterlab_cognos_dashboard_embedded-3.0.0.dist-info/RECORD
