Metadata-Version: 2.1
Name: jupyterlab-cognos-dashboard-embedded
Version: 3.0.0
Summary: Cognos Dashboard Embedded for JupyterLab
Home-page: https://github.com/IBM/jupyterlab-cognos-dashboard-embedded
Author: James Reeve
License: Apache 2
Keywords: Jupyter,JupyterLab,JupyterLab3,S3
Platform: Linux
Platform: Mac OS X
Platform: Windows
Classifier: Intended Audience :: Developers
Classifier: Intended Audience :: Education
Classifier: Intended Audience :: Science/Research
Classifier: License :: OSI Approved :: Apache Software License
Classifier: Programming Language :: Python
Classifier: Programming Language :: Python :: 3
Classifier: Framework :: Jupyter
Requires-Python: >=3.6
Requires-Dist: notebook
Requires-Dist: requests
Requires-Dist: traitlets
Requires-Dist: jupyter-server
Requires-Dist: jupyterlab (>=2.0.0)
Provides-Extra: dev
Requires-Dist: jupyter-packaging (~=0.7.9) ; extra == 'dev'
